__init__.py
constellation/__init__.py
constellation/all.py
constellation/base.py
constellation/helpers.py
constellation/relay.py
constellation/ui.py
constellation/instrument_control/__init__.py
constellation/instrument_control/all.py
constellation/instrument_control/instrument_control.py
constellation/instrument_control/oscilloscope/__init__.py
constellation/instrument_control/oscilloscope/oscilloscope_ctg.py
constellation/instrument_control/oscilloscope/oscilloscope_gui.py
constellation/instrument_control/oscilloscope/drivers/LeCroy_WaveRunner44Xi_dvr.py
constellation/instrument_control/oscilloscope/drivers/Rigol_DS1000Z_dvr.py
constellation/instrument_control/oscilloscope/drivers/__init__.py
constellation/instrument_control/spectrum_analyzer/__init__.py
constellation/instrument_control/spectrum_analyzer/spectrum_analyzer_ctg.py
constellation/instrument_control/spectrum_analyzer/drivers/RohdeSchwarz_FSE_dvr.py
constellation/instrument_control/spectrum_analyzer/drivers/Siglent_SSA3000X_dvr.py
constellation/instrument_control/spectrum_analyzer/drivers/__init__.py
constellation/instrument_control/to_reformat/categories/__init__.py
constellation/instrument_control/to_reformat/categories/digital_multimeter_ctg.py
constellation/instrument_control/to_reformat/categories/lock_in_amplifier_ctg.py
constellation/instrument_control/to_reformat/categories/rf_power_sensor_ctg.py
constellation/instrument_control/to_reformat/categories/rf_signal_generator_ctg.py
constellation/instrument_control/to_reformat/categories/temperature_controller_ctg.py
constellation/instrument_control/to_reformat/drivers/Agilent_E4400_dvr.py
constellation/instrument_control/to_reformat/drivers/Keysight_33600A_dvr.py
constellation/instrument_control/to_reformat/drivers/Keysight_34400_dvr.py
constellation/instrument_control/to_reformat/drivers/Keysight_8360L_dvr.py
constellation/instrument_control/to_reformat/drivers/LakeShore_Model335_dvr.py
constellation_core-0.0.0.dev0.dist-info/licenses/LICENSE
constellation_core-0.0.0.dev0.dist-info/METADATA
constellation_core-0.0.0.dev0.dist-info/WHEEL
constellation_core-0.0.0.dev0.dist-info/top_level.txt
constellation_core-0.0.0.dev0.dist-info/RECORD
