Metadata-Version: 2.4
Name: constellation-core
Version: 0.0.0.dev0
Summary: Modular instrument control and lab access via Python
Author-email: Grant Giesbrecht <grant.giesbrecht@colorado.edu>
License-Expression: BSD-2-Clause
Project-URL: Homepage, https://github.com/Grant-Giesbrecht/constellation
Project-URL: Issues, https://github.com/Grant-Giesbrecht/constellation/issues
Classifier: Programming Language :: Python :: 3
Classifier: Operating System :: OS Independent
Requires-Python: >=3.10
License-File: LICENSE
Requires-Dist: numpy>=1.0.0
Requires-Dist: pyvisa>=1.0.0
Requires-Dist: pylogfile>=0.3.0
Requires-Dist: h5py>=3.11.0
Requires-Dist: colorama>=0.4.0
Requires-Dist: pyfrost-network>=0.0.0.dev0
Requires-Dist: tabulate>=0.9.0
Requires-Dist: zhinst>=24.0.0
Requires-Dist: jarnsaxa>=0.0.0
Requires-Dist: pyvicp>=1.0.0
Dynamic: license-file
